edc_timepoint/__init__.py
edc_timepoint/apps.py
edc_timepoint/choices.py
edc_timepoint/constants.py
edc_timepoint/form_mixin.py
edc_timepoint/model_mixins.py
edc_timepoint/timepoint.py
edc_timepoint/timepoint_collection.py
edc_timepoint/timepoint_lookup.py
edc_timepoint/utils.py
edc_timepoint/models/__init__.py
edc_timepoint/models/signals.py
edc_timepoint/tests/__init__.py
edc_timepoint/tests/consents.py
edc_timepoint/tests/holidays.csv
edc_timepoint/tests/models.py
edc_timepoint/tests/test_settings.py
edc_timepoint/tests/urls.py
edc_timepoint/tests/visit_schedule.py
edc_timepoint/tests/etc/user-aes-local.key
edc_timepoint/tests/etc/user-aes-restricted.key
edc_timepoint/tests/etc/user-rsa-local-private.pem
edc_timepoint/tests/etc/user-rsa-local-public.pem
edc_timepoint/tests/etc/user-rsa-restricted-private.pem
edc_timepoint/tests/etc/user-rsa-restricted-public.pem
edc_timepoint/tests/etc/user-salt-local.key
edc_timepoint/tests/etc/user-salt-restricted.key
edc_timepoint/tests/tests/__init__.py
edc_timepoint/tests/tests/test_timepoints.py
edc_timepoint-1.0.1.dist-info/licenses/AUTHORS.rst
edc_timepoint-1.0.1.dist-info/licenses/LICENSE
edc_timepoint-1.0.1.dist-info/METADATA
edc_timepoint-1.0.1.dist-info/WHEEL
edc_timepoint-1.0.1.dist-info/top_level.txt
edc_timepoint-1.0.1.dist-info/RECORD
